swemaps/__init__.py
swemaps/_fetcher.py
swemaps/_version.py
swemaps/py.typed
swemaps/utils.py
swemaps/data/fa.parquet
swemaps/data/kommun.parquet
swemaps/data/lan.parquet
swemaps-0.2.1.dist-info/METADATA
swemaps-0.2.1.dist-info/WHEEL
swemaps-0.2.1.dist-info/licenses/LICENSE
swemaps-0.2.1.dist-info/RECORD
