Metadata-Version: 2.3
Name: swemaps
Version: 0.2.1
Summary: Maps of Sweden in GeoParquet for easy usage.
Project-URL: Repository, https://github.com/stefur/swemaps
Author-email: Stefan Furne <stefan@furne.net>
License-Expression: MIT
License-File: LICENSE
Keywords: choropleth,geoarrow,geopandas,geoparquet,maps,pyarrow,sweden
Classifier: License :: OSI Approved :: MIT License
Classifier: Programming Language :: Python :: 3 :: Only
Classifier: Programming Language :: Python :: 3.9
Classifier: Programming Language :: Python :: 3.10
Classifier: Programming Language :: Python :: 3.11
Classifier: Programming Language :: Python :: 3.12
Requires-Python: >=3.9
Requires-Dist: pooch>=1.8.2
Provides-Extra: geojson
Requires-Dist: geoarrow-rust-io>=0.3.0; extra == 'geojson'
